Metadata-Version: 1.2
Name: tablepy
Version: 0.0.0.1
Summary: table generator for python
Home-page: https://github.com/JulianWww/tables
Author: Julian Wandhoven
Author-email: julian.wandhoven@fgz.ch
License: wtfpl
Project-URL: documentation, https://tablepy.readthedocs.io/en/latest/index.html
Keywords: tables,rendering
Platform: UNKNOWN
Classifier: Development Status :: 2 - Pre-Alpha
Classifier: Intended Audience :: Developers
Classifier: Topic :: Software Development :: Build Tools
Classifier: License :: OSI Approved :: MIT License
Classifier: Programming Language :: Python :: 3.6
Classifier: Programming Language :: Python :: 3
